windpower_upc.py
windpower_upc-0.0.2.dist-info/METADATA
windpower_upc-0.0.2.dist-info/WHEEL
windpower_upc-0.0.2.dist-info/top_level.txt
windpower_upc-0.0.2.dist-info/RECORD
