Metadata-Version: 2.1
Name: windpower-upc
Version: 0.0.2
Summary: A module for wind power prediction
Home-page: https://github.com/962516016/windpower_upc
Author: yuange_liu, daobin_luo
Author-email: liuyuange811@gmail.com, luodaobin2001@gmail.com
License: MIT
Classifier: Programming Language :: Python
Classifier: Programming Language :: Python :: 3
Classifier: Programming Language :: Python :: 3.5
Classifier: Programming Language :: Python :: 3.5
Classifier: Programming Language :: Python :: 3.6
Classifier: Programming Language :: Python :: 3.7
Classifier: Programming Language :: Python :: Implementation :: CPython
Requires-Dist: requests <=2.31.0
